yamlforge/__init__.py
yamlforge/_version.py
yamlforge/main.py
yamlforge/utils.py
yamlforge/core/__init__.py
yamlforge/core/converter.py
yamlforge/core/credentials.py
yamlforge/core/rosa_versions.py
yamlforge/defaults/alibaba.yaml
yamlforge/defaults/aws.yaml
yamlforge/defaults/azure.yaml
yamlforge/defaults/cnv.yaml
yamlforge/defaults/core.yaml
yamlforge/defaults/gcp.yaml
yamlforge/defaults/ibm_classic.yaml
yamlforge/defaults/ibm_vpc.yaml
yamlforge/defaults/oci.yaml
yamlforge/defaults/openshift.yaml
yamlforge/defaults/vmware.yaml
yamlforge/defaults/openshift_operators/backup/oadp.yaml
yamlforge/defaults/openshift_operators/core/gitops.yaml
yamlforge/defaults/openshift_operators/core/logging.yaml
yamlforge/defaults/openshift_operators/core/monitoring.yaml
yamlforge/defaults/openshift_operators/core/pipelines.yaml
yamlforge/defaults/openshift_operators/core/serverless.yaml
yamlforge/defaults/openshift_operators/core/service_mesh.yaml
yamlforge/defaults/openshift_operators/core/storage.yaml
yamlforge/defaults/openshift_operators/networking/metallb.yaml
yamlforge/defaults/openshift_operators/networking/submariner.yaml
yamlforge/defaults/openshift_operators/security/cert_manager.yaml
yamlforge/docs/yamlforge-schema.json
yamlforge/mappings/cloud_patterns.yaml
yamlforge/mappings/images.yaml
yamlforge/mappings/locations.yaml
yamlforge/mappings/storage_costs.yaml
yamlforge/mappings/cnv/defaults.yaml
yamlforge/mappings/flavors/alibaba.yaml
yamlforge/mappings/flavors/aro.yaml
yamlforge/mappings/flavors/aws.yaml
yamlforge/mappings/flavors/azure.yaml
yamlforge/mappings/flavors/cheapest.yaml
yamlforge/mappings/flavors/cnv.yaml
yamlforge/mappings/flavors/gcp.yaml
yamlforge/mappings/flavors/generic.yaml
yamlforge/mappings/flavors/ibm_classic.yaml
yamlforge/mappings/flavors/ibm_vpc.yaml
yamlforge/mappings/flavors/oci.yaml
yamlforge/mappings/flavors/vmware.yaml
yamlforge/mappings/flavors_openshift/openshift_alibaba.yaml
yamlforge/mappings/flavors_openshift/openshift_aws.yaml
yamlforge_infra-1.0.0b5.dist-info/licenses/LICENSE
yamlforge_infra-1.0.0b5.dist-info/METADATA
yamlforge_infra-1.0.0b5.dist-info/WHEEL
yamlforge_infra-1.0.0b5.dist-info/entry_points.txt
yamlforge_infra-1.0.0b5.dist-info/top_level.txt
yamlforge_infra-1.0.0b5.dist-info/RECORD
