Metadata-Version: 2.4
Name: yamlforge-infra
Version: 1.0.0b5
Summary: Multi-Cloud Infrastructure as Code and PaaS Management Suite (BETA - Feature Complete)
Author: Patrick T. Rutledge III
License-Expression: Apache-2.0
Project-URL: Homepage, https://github.com/rut31337/YamlForge
Project-URL: Repository, https://github.com/rut31337/YamlForge
Project-URL: Issues, https://github.com/rut31337/YamlForge/issues
Keywords: terraform,multi-cloud,infrastructure-as-code,paas,management,yaml,aws,azure,gcp,openshift,kubernetes
Classifier: Development Status :: 4 - Beta
Classifier: Intended Audience :: Developers
Classifier: Intended Audience :: System Administrators
Classifier: Operating System :: OS Independent
Classifier: Programming Language :: Python :: 3
Classifier: Programming Language :: Python :: 3.8
Classifier: Programming Language :: Python :: 3.9
Classifier: Programming Language :: Python :: 3.10
Classifier: Programming Language :: Python :: 3.11
Classifier: Topic :: Software Development :: Code Generators
Classifier: Topic :: System :: Systems Administration
Requires-Python: >=3.8
License-File: LICENSE
Requires-Dist: PyYAML>=6.0.2
Requires-Dist: boto3>=1.39.0
Requires-Dist: google-cloud-compute>=1.32.0
Requires-Dist: google-cloud-dns>=0.35.0
Requires-Dist: oci>=2.155.0
Requires-Dist: alibabacloud-ecs20140526>=7.0.0
Requires-Dist: alibabacloud-tea-openapi>=0.3.0
Requires-Dist: ibm-cloud-sdk-core>=3.16.7
Requires-Dist: ibm-vpc>=0.10.0
Requires-Dist: requests>=2.32.0
Provides-Extra: dev
Requires-Dist: pytest>=6.0; extra == "dev"
Requires-Dist: black>=21.0; extra == "dev"
Requires-Dist: flake8>=3.8; extra == "dev"
Requires-Dist: mypy>=0.800; extra == "dev"
Requires-Dist: vulture>=2.0; extra == "dev"
Provides-Extra: docs
Requires-Dist: sphinx>=4.0; extra == "docs"
Requires-Dist: sphinx-rtd-theme>=0.5; extra == "docs"
Dynamic: license-file
